luvina
