Metadata-Version: 1.0
Name: luvina
Version: 0.0.24
Summary: High-level API for Natural Language Processing in NLTK
Home-page: https://github.com/oarriaga/luvina
Author: Octavio Arriaga
Author-email: arriaga.camargo@gmail.com
License: MIT
Platform: UNKNOWN
